{"summary":{"n_matches":29,"n_with_market":27,"n_correct":24,"avg_brier_model":0.1997,"avg_brier_market":0.1586,"avg_log_loss_model":0.5909,"avg_log_loss_market":0.4931,"coin_flip_brier":0.25,"coin_flip_log_loss":0.6931,"brier_skill_vs_coin":0.2012,"brier_skill_vs_market":-0.2591,"logistic_scale":null},"entries":[{"event_id":"760486","run_date":"2026-07-14","round":"Round of 32","home_team":"South Africa","away_team":"Canada","advanced_team":"Canada","model_prob":0.432906,"market_prob":null,"brier_model":0.187408,"brier_market":null,"log_loss_model":0.567231,"log_loss_market":null},{"event_id":"760487","run_date":"2026-07-14","round":"Round of 32","home_team":"Brazil","away_team":"Japan","advanced_team":"Brazil","model_prob":0.590561,"market_prob":null,"brier_model":0.167641,"brier_market":null,"log_loss_model":0.526683,"log_loss_market":null},{"event_id":"760488","run_date":"2026-07-14","round":"Round of 32","home_team":"Netherlands","away_team":"Morocco","advanced_team":"Morocco","model_prob":0.595546,"market_prob":0.569887,"brier_model":0.354675,"brier_market":0.324772,"log_loss_model":0.905217,"log_loss_market":0.843708},{"event_id":"760489","run_date":"2026-07-14","round":"Round of 32","home_team":"Germany","away_team":"Paraguay","advanced_team":"Paraguay","model_prob":0.589993,"market_prob":0.822779,"brier_model":0.348091,"brier_market":0.676965,"log_loss_model":0.89158,"log_loss_market":1.730358},{"event_id":"760490","run_date":"2026-07-14","round":"Round of 32","home_team":"Ivory Coast","away_team":"Norway","advanced_team":"Norway","model_prob":0.483899,"market_prob":0.402258,"brier_model":0.234159,"brier_market":0.161812,"log_loss_model":0.661453,"log_loss_market":0.514596},{"event_id":"760491","run_date":"2026-07-14","round":"Round of 32","home_team":"Mexico","away_team":"Ecuador","advanced_team":"Mexico","model_prob":0.564536,"market_prob":0.600796,"brier_model":0.189629,"brier_market":0.159364,"log_loss_model":0.571752,"log_loss_market":0.5095},{"event_id":"760492","run_date":"2026-07-14","round":"Round of 32","home_team":"France","away_team":"Sweden","advanced_team":"France","model_prob":0.647959,"market_prob":0.829683,"brier_model":0.123933,"brier_market":0.029008,"log_loss_model":0.433928,"log_loss_market":0.186712},{"event_id":"760493","run_date":"2026-07-14","round":"Round of 32","home_team":"Belgium","away_team":"Senegal","advanced_team":"Belgium","model_prob":0.535342,"market_prob":0.606248,"brier_model":0.215907,"brier_market":0.15504,"log_loss_model":0.62485,"log_loss_market":0.500466},{"event_id":"760494","run_date":"2026-07-14","round":"Round of 32","home_team":"United States","away_team":"Bosnia & Herzegovina","advanced_team":"United States","model_prob":0.586927,"market_prob":0.797569,"brier_model":0.170629,"brier_market":0.040978,"log_loss_model":0.532854,"log_loss_market":0.226187},{"event_id":"760495","run_date":"2026-07-14","round":"Round of 32","home_team":"England","away_team":"Congo DR","advanced_team":"England","model_prob":0.622741,"market_prob":0.843637,"brier_model":0.142324,"brier_market":0.024449,"log_loss_model":0.473624,"log_loss_market":0.170033},{"event_id":"760496","run_date":"2026-07-14","round":"Round of 32","home_team":"Portugal","away_team":"Croatia","advanced_team":"Portugal","model_prob":0.599155,"market_prob":0.692643,"brier_model":0.160676,"brier_market":0.094468,"log_loss_model":0.512234,"log_loss_market":0.36724},{"event_id":"760497","run_date":"2026-07-14","round":"Round of 32","home_team":"Spain","away_team":"Austria","advanced_team":"Spain","model_prob":0.661444,"market_prob":0.82631,"brier_model":0.11462,"brier_market":0.030168,"log_loss_model":0.41333,"log_loss_market":0.190785},{"event_id":"760498","run_date":"2026-07-14","round":"Round of 32","home_team":"Switzerland","away_team":"Algeria","advanced_team":"Switzerland","model_prob":0.598027,"market_prob":0.63993,"brier_model":0.161582,"brier_market":0.12965,"log_loss_model":0.514119,"log_loss_market":0.446397},{"event_id":"760499","run_date":"2026-07-14","round":"Round of 32","home_team":"Australia","away_team":"Egypt","advanced_team":"Egypt","model_prob":0.467044,"market_prob":0.437276,"brier_model":0.21813,"brier_market":0.19121,"log_loss_model":0.629317,"log_loss_market":0.574965},{"event_id":"760500","run_date":"2026-07-14","round":"Round of 32","home_team":"Argentina","away_team":"Cape Verde","advanced_team":"Argentina","model_prob":0.644238,"market_prob":0.888968,"brier_model":0.126566,"brier_market":0.012328,"log_loss_model":0.439687,"log_loss_market":0.117694},{"event_id":"760501","run_date":"2026-07-14","round":"Round of 32","home_team":"Colombia","away_team":"Ghana","advanced_team":"Colombia","model_prob":0.587878,"market_prob":0.785516,"brier_model":0.169845,"brier_market":0.046003,"log_loss_model":0.531236,"log_loss_market":0.241414},{"event_id":"760502","run_date":"2026-07-14","round":"Round of 16","home_team":"Canada","away_team":"Morocco","advanced_team":"Morocco","model_prob":0.474508,"market_prob":0.313187,"brier_model":0.225158,"brier_market":0.098086,"log_loss_model":0.643421,"log_loss_market":0.375693},{"event_id":"760503","run_date":"2026-07-14","round":"Round of 16","home_team":"Paraguay","away_team":"France","advanced_team":"France","model_prob":0.359763,"market_prob":0.115146,"brier_model":0.12943,"brier_market":0.013259,"log_loss_model":0.445918,"log_loss_market":0.122333},{"event_id":"760504","run_date":"2026-07-14","round":"Round of 16","home_team":"Brazil","away_team":"Norway","advanced_team":"Norway","model_prob":0.558236,"market_prob":0.669504,"brier_model":0.311627,"brier_market":0.448236,"log_loss_model":0.816979,"log_loss_market":1.107162},{"event_id":"760505","run_date":"2026-07-14","round":"Round of 16","home_team":"Mexico","away_team":"England","advanced_team":"England","model_prob":0.461904,"market_prob":0.444063,"brier_model":0.213355,"brier_market":0.197192,"log_loss_model":0.619717,"log_loss_market":0.587099},{"event_id":"760506","run_date":"2026-07-14","round":"Round of 16","home_team":"Portugal","away_team":"Spain","advanced_team":"Spain","model_prob":0.456826,"market_prob":0.358203,"brier_model":0.20869,"brier_market":0.128309,"log_loss_model":0.610326,"log_loss_market":0.443483},{"event_id":"760507","run_date":"2026-07-14","round":"Round of 16","home_team":"United States","away_team":"Belgium","advanced_team":"Belgium","model_prob":0.458766,"market_prob":0.499576,"brier_model":0.210467,"brier_market":0.249576,"log_loss_model":0.613904,"log_loss_market":0.692299},{"event_id":"760508","run_date":"2026-07-14","round":"Round of 16","home_team":"Switzerland","away_team":"Colombia","advanced_team":"Switzerland","model_prob":0.483782,"market_prob":0.411604,"brier_model":0.266481,"brier_market":0.34621,"log_loss_model":0.726121,"log_loss_market":0.887693},{"event_id":"760509","run_date":"2026-07-14","round":"Round of 16","home_team":"Argentina","away_team":"Egypt","advanced_team":"Argentina","model_prob":0.622686,"market_prob":0.818006,"brier_model":0.142366,"brier_market":0.033122,"log_loss_model":0.473713,"log_loss_market":0.200886},{"event_id":"760510","run_date":"2026-07-14","round":"Quarterfinals","home_team":"France","away_team":"Morocco","advanced_team":"France","model_prob":0.633495,"market_prob":0.741527,"brier_model":0.134326,"brier_market":0.066808,"log_loss_model":0.456502,"log_loss_market":0.299044},{"event_id":"760511","run_date":"2026-07-14","round":"Quarterfinals","home_team":"Spain","away_team":"Belgium","advanced_team":"Spain","model_prob":0.563475,"market_prob":0.718439,"brier_model":0.190554,"brier_market":0.079276,"log_loss_model":0.573633,"log_loss_market":0.330674},{"event_id":"760512","run_date":"2026-07-14","round":"Quarterfinals","home_team":"Norway","away_team":"England","advanced_team":"England","model_prob":0.470635,"market_prob":0.36828,"brier_model":0.221497,"brier_market":0.13563,"log_loss_model":0.636077,"log_loss_market":0.459309},{"event_id":"760513","run_date":"2026-07-14","round":"Quarterfinals","home_team":"Argentina","away_team":"Switzerland","advanced_team":"Argentina","model_prob":0.58811,"market_prob":0.707604,"brier_model":0.169653,"brier_market":0.085495,"log_loss_model":0.530842,"log_loss_market":0.345871},{"event_id":"760514","run_date":"2026-07-14","round":"Semifinals","home_team":"France","away_team":"Spain","advanced_team":"Spain","model_prob":0.531603,"market_prob":0.568757,"brier_model":0.282602,"brier_market":0.323484,"log_loss_model":0.75844,"log_loss_market":0.841083}]}